sunjeet_tools/__init__.py
sunjeet_tools/cli.py
sunjeet_tools/git_tools.py
sunjeet_tools/utils.py
sunjeet_tools-0.1.1.dist-info/licenses/LICENSE
sunjeet_tools-0.1.1.dist-info/METADATA
sunjeet_tools-0.1.1.dist-info/WHEEL
sunjeet_tools-0.1.1.dist-info/entry_points.txt
sunjeet_tools-0.1.1.dist-info/top_level.txt
sunjeet_tools-0.1.1.dist-info/RECORD
