Metadata-Version: 2.4
Name: sunjeet-tools
Version: 0.1.1
Summary: Personal utility tools by Sunjeet
Author: Sunjeet
License: MIT
Project-URL: Homepage, https://github.com/SunjeetKajla/sunjeet-tools
Project-URL: Documentation, https://sunjeet-tools.readthedocs.io/
Project-URL: Source, https://github.com/SunjeetKajla/sunjeet-tools
Project-URL: Changelog, https://github.com/SunjeetKajla/sunjeet-tools/blob/main/CHANGELOG.md
Requires-Python: >=3.7
License-File: LICENSE
Dynamic: license-file
